[
	{ "name" : "grid_component" , "topic" : "/Server/Guide/Design/View/Grid/Grid Properties in Detail.html" },
	{ "name" : "webprojectpropertiesbuilder" , "topic" : "/Server/Reference/Design/WebProjectSettings.html" },
	{ "name" : "pagelayoutcomponent" , "topic" : "/Server/Reference/Design/Page Layout Component.html" },
	{ "name" : "navigationsystembuilder" , "topic" : "/Server/Reference/Design/Navigation System.html" },
	{ "name" : "applauncher" , "topic" : "/Server/Reference/Design/AppLauncher Properties.html" },
	{ "name" : "calendarcomponent" , "topic" : "/Server/Reference/Design/Calendar Component Properties.html" },
	{ "name" : "googlemap" , "topic" : "/Server/Reference/Design/Google Map Properties.html" },
	{ "name" : "imagegallerycomponent" , "topic" : "/Server/Reference/Design/Image Gallery Properties.html" },
	{ "name" : "videoplayercomponent" , "topic" : "/Server/Reference/Design/Video Player Component Properties.html" },
	{ "name" : "tabbeduicomponent" , "topic" : "/Server/Reference/Design/Tabbed UI Component Properties.html" },
	{ "name" : "gridcomponent" , "topic" : "/Server/Reference/Design/Grid Component Search Part.html" },
	{ "name" : "gridfieldproperties" , "topic" : "/Server/Reference/Design/Grid Field Properties.html" },
	{ "name" : "websecurity" , "topic" : "/Server/Reference/Design/Web Security Configuration.html" }
] 
     
	 
	 
	